rocket_ml/__init__.py
rocket_ml/db/__init__.py
rocket_ml/db/impala.py
rocket_ml/plot/__init__.py
rocket_ml-0.1.0.dist-info/METADATA
rocket_ml-0.1.0.dist-info/WHEEL
rocket_ml-0.1.0.dist-info/entry_points.txt
rocket_ml-0.1.0.dist-info/RECORD
