Metadata-Version: 2.4
Name: rocket-ml
Version: 0.1.0
Summary: Add your description here
Author-email: mingminyu <yu_mingm623@163.com>
Requires-Python: >=3.12
Provides-Extra: impala
Requires-Dist: impyla; extra == 'impala'
